sphinxcontrib_httpdomain_update-1.3.1-py2.7-nspkg.pth
sphinxcontrib/httpdomain.py
sphinxcontrib/autohttp/bottle.py
sphinxcontrib/autohttp/common.py
sphinxcontrib/autohttp/flask.py
sphinxcontrib/autohttp/tornado.py
sphinxcontrib/autohttp/__init__.py
sphinxcontrib_httpdomain_update-1.3.1.dist-info/DESCRIPTION.rst
sphinxcontrib_httpdomain_update-1.3.1.dist-info/METADATA
sphinxcontrib_httpdomain_update-1.3.1.dist-info/metadata.json
sphinxcontrib_httpdomain_update-1.3.1.dist-info/namespace_packages.txt
sphinxcontrib_httpdomain_update-1.3.1.dist-info/RECORD
sphinxcontrib_httpdomain_update-1.3.1.dist-info/top_level.txt
sphinxcontrib_httpdomain_update-1.3.1.dist-info/WHEEL
